omdev/.omlish-manifests.json
omdev/README.md
omdev/__about__.py
omdev/__init__.py
omdev/cmake.py
omdev/imgur.py
omdev/pip.py
omdev/tagstrings.py
omdev/amalg/__init__.py
omdev/amalg/__main__.py
omdev/amalg/info.py
omdev/amalg/sources.py
omdev/amalg/cli/__init__.py
omdev/amalg/cli/main.py
omdev/amalg/gen/__init__.py
omdev/amalg/gen/gen.py
omdev/amalg/gen/imports.py
omdev/amalg/gen/manifests.py
omdev/amalg/gen/resources.py
omdev/amalg/gen/srcfiles.py
omdev/amalg/gen/strip.py
omdev/amalg/gen/types.py
omdev/amalg/gen/typing.py
omdev/cache/__init__.py
omdev/cache/compute/__init__.py
omdev/cache/compute/cache.py
omdev/cache/compute/contexts.py
omdev/cache/compute/currents.py
omdev/cache/compute/fns.py
omdev/cache/compute/resolvers.py
omdev/cache/compute/storage.py
omdev/cache/compute/types.py
omdev/cache/data/__init__.py
omdev/cache/data/actions.py
omdev/cache/data/cache.py
omdev/cache/data/consts.py
omdev/cache/data/defaults.py
omdev/cache/data/manifests.py
omdev/cache/data/specs.py
omdev/capi/__init__.py
omdev/capi/darwin/__init__.py
omdev/capi/darwin/aps.py
omdev/capi/darwin/ax.py
omdev/capi/darwin/cf.py
omdev/capi/darwin/cg.py
omdev/capi/linux/__init__.py
omdev/capi/linux/x11.py
omdev/cc/__init__.py
omdev/cc/__main__.py
omdev/cc/cdeps.py
omdev/cc/cdeps.toml
omdev/cc/cli.py
omdev/cc/srclangs.py
omdev/cexts/__init__.py
omdev/cexts/_boilerplate.cc
omdev/cexts/build.py
omdev/cexts/cmake.py
omdev/cexts/importhook.py
omdev/cexts/magic.py
omdev/cexts/scan.py
omdev/cexts/_distutils/LICENSE
omdev/cexts/_distutils/__init__.py
omdev/cexts/_distutils/build_ext.py
omdev/cexts/_distutils/dir_util.py
omdev/cexts/_distutils/errors.py
omdev/cexts/_distutils/extension.py
omdev/cexts/_distutils/file_util.py
omdev/cexts/_distutils/modified.py
omdev/cexts/_distutils/spawn.py
omdev/cexts/_distutils/sysconfig.py
omdev/cexts/_distutils/util.py
omdev/cexts/_distutils/version.py
omdev/cexts/_distutils/compilers/__init__.py
omdev/cexts/_distutils/compilers/ccompiler.py
omdev-0.0.0.dev516.dist-info/licenses/LICENSE
omdev-0.0.0.dev516.dist-info/METADATA
omdev-0.0.0.dev516.dist-info/WHEEL
omdev-0.0.0.dev516.dist-info/entry_points.txt
omdev-0.0.0.dev516.dist-info/top_level.txt
omdev-0.0.0.dev516.dist-info/RECORD
