Metadata-Version: 2.4
Name: omdev
Version: 0.0.0.dev516
Summary: omdev
Author: wrmsr
License-Expression: BSD-3-Clause
Project-URL: source, https://github.com/wrmsr/omlish
Classifier: Development Status :: 2 - Pre-Alpha
Classifier: Intended Audience :: Developers
Classifier: Operating System :: OS Independent
Classifier: Operating System :: POSIX
Classifier: Programming Language :: Python :: 3
Classifier: Programming Language :: Python :: 3.13
Requires-Python: >=3.13
License-File: LICENSE
Requires-Dist: omlish==0.0.0.dev516
Provides-Extra: all
Requires-Dist: black~=26.1; extra == "all"
Requires-Dist: pycparser~=3.0; extra == "all"
Requires-Dist: pcpp~=1.30; extra == "all"
Requires-Dist: docutils~=0.22; extra == "all"
Requires-Dist: markdown-it-py~=4.0; extra == "all"
Requires-Dist: mdit-py-plugins~=0.5; extra == "all"
Requires-Dist: pygments~=2.19; extra == "all"
Requires-Dist: mypy~=1.19; extra == "all"
Requires-Dist: gprof2dot~=2025.4; extra == "all"
Requires-Dist: segno~=1.6; extra == "all"
Requires-Dist: rich~=14.3; extra == "all"
Requires-Dist: textual~=7.4; extra == "all"
Requires-Dist: textual-dev~=1.8; extra == "all"
Requires-Dist: textual-speedups~=0.2; extra == "all"
Provides-Extra: black
Requires-Dist: black~=26.1; extra == "black"
Provides-Extra: c
Requires-Dist: pycparser~=3.0; extra == "c"
Requires-Dist: pcpp~=1.30; extra == "c"
Provides-Extra: doc
Requires-Dist: docutils~=0.22; extra == "doc"
Requires-Dist: markdown-it-py~=4.0; extra == "doc"
Requires-Dist: mdit-py-plugins~=0.5; extra == "doc"
Requires-Dist: pygments~=2.19; extra == "doc"
Provides-Extra: mypy
Requires-Dist: mypy~=1.19; extra == "mypy"
Provides-Extra: prof
Requires-Dist: gprof2dot~=2025.4; extra == "prof"
Provides-Extra: qr
Requires-Dist: segno~=1.6; extra == "qr"
Provides-Extra: tui
Requires-Dist: rich~=14.3; extra == "tui"
Requires-Dist: textual~=7.4; extra == "tui"
Requires-Dist: textual-dev~=1.8; extra == "tui"
Requires-Dist: textual-speedups~=0.2; extra == "tui"
Dynamic: license-file
